odoo10_addon_web_switch_company_warning-10.0.0.1.1.99.dev1-py2.7-nspkg.pth
odoo/addons/web_switch_company_warning/README.rst
odoo/addons/web_switch_company_warning/__init__.py
odoo/addons/web_switch_company_warning/__manifest__.py
odoo/addons/web_switch_company_warning/i18n/web_switch_company_warning.pot
odoo/addons/web_switch_company_warning/static/description/icon.png
odoo/addons/web_switch_company_warning/static/src/js/switch_company_warning.js
odoo/addons/web_switch_company_warning/static/src/js/switch_company_warning_worker.js
odoo/addons/web_switch_company_warning/static/src/xml/switch_company_warning.xml
odoo/addons/web_switch_company_warning/view/view.xml
odoo10_addon_web_switch_company_warning-10.0.0.1.1.99.dev1.dist-info/METADATA
odoo10_addon_web_switch_company_warning-10.0.0.1.1.99.dev1.dist-info/RECORD
odoo10_addon_web_switch_company_warning-10.0.0.1.1.99.dev1.dist-info/WHEEL
odoo10_addon_web_switch_company_warning-10.0.0.1.1.99.dev1.dist-info/namespace_packages.txt
odoo10_addon_web_switch_company_warning-10.0.0.1.1.99.dev1.dist-info/top_level.txt
