Metadata-Version: 2.1
Name: odoo10-addon-web-switch-company-warning
Version: 10.0.0.1.1.99.dev1
Summary: Show a warning if current company has been switched in another tab or window.
Home-page: http://akretion.com
Author: Akretion, Odoo Community Association (OCA)
Author-email: support@odoo-community.org
License: AGPL-3
Platform: UNKNOWN
Classifier: Programming Language :: Python
Classifier: Framework :: Odoo
Classifier: License :: OSI Approved :: GNU Affero General Public License v3
Requires-Python: ~=2.7
Requires-Dist: odoo (<10.1dev,>=10.0)
